fastqc_jre/jdk-17.0.15+6-jre/NOTICE
fastqc_jre/jdk-17.0.15+6-jre/release
fastqc_jre/jdk-17.0.15+6-jre/bin/WinFallbackLookup.dll
fastqc_jre/jdk-17.0.15+6-jre/bin/api-ms-win-core-console-l1-1-0.dll
fastqc_jre/jdk-17.0.15+6-jre/bin/api-ms-win-core-console-l1-2-0.dll
fastqc_jre/jdk-17.0.15+6-jre/bin/api-ms-win-core-datetime-l1-1-0.dll
fastqc_jre/jdk-17.0.15+6-jre/bin/api-ms-win-core-debug-l1-1-0.dll
fastqc_jre/jdk-17.0.15+6-jre/bin/api-ms-win-core-errorhandling-l1-1-0.dll
fastqc_jre/jdk-17.0.15+6-jre/bin/api-ms-win-core-fibers-l1-1-0.dll
fastqc_jre/jdk-17.0.15+6-jre/bin/api-ms-win-core-fibers-l1-1-1.dll
fastqc_jre/jdk-17.0.15+6-jre/bin/api-ms-win-core-file-l1-1-0.dll
fastqc_jre/jdk-17.0.15+6-jre/bin/api-ms-win-core-file-l1-2-0.dll
fastqc_jre/jdk-17.0.15+6-jre/bin/api-ms-win-core-file-l2-1-0.dll
fastqc_jre/jdk-17.0.15+6-jre/bin/api-ms-win-core-handle-l1-1-0.dll
fastqc_jre/jdk-17.0.15+6-jre/bin/api-ms-win-core-heap-l1-1-0.dll
fastqc_jre/jdk-17.0.15+6-jre/bin/api-ms-win-core-interlocked-l1-1-0.dll
fastqc_jre/jdk-17.0.15+6-jre/bin/api-ms-win-core-kernel32-legacy-l1-1-1.dll
fastqc_jre/jdk-17.0.15+6-jre/bin/api-ms-win-core-libraryloader-l1-1-0.dll
fastqc_jre/jdk-17.0.15+6-jre/bin/api-ms-win-core-localization-l1-2-0.dll
fastqc_jre/jdk-17.0.15+6-jre/bin/api-ms-win-core-memory-l1-1-0.dll
fastqc_jre/jdk-17.0.15+6-jre/bin/api-ms-win-core-namedpipe-l1-1-0.dll
fastqc_jre/jdk-17.0.15+6-jre/bin/api-ms-win-core-processenvironment-l1-1-0.dll
fastqc_jre/jdk-17.0.15+6-jre/bin/api-ms-win-core-processthreads-l1-1-0.dll
fastqc_jre/jdk-17.0.15+6-jre/bin/api-ms-win-core-processthreads-l1-1-1.dll
fastqc_jre/jdk-17.0.15+6-jre/bin/api-ms-win-core-profile-l1-1-0.dll
fastqc_jre/jdk-17.0.15+6-jre/bin/api-ms-win-core-rtlsupport-l1-1-0.dll
fastqc_jre/jdk-17.0.15+6-jre/bin/api-ms-win-core-string-l1-1-0.dll
fastqc_jre/jdk-17.0.15+6-jre/bin/api-ms-win-core-synch-l1-1-0.dll
fastqc_jre/jdk-17.0.15+6-jre/bin/api-ms-win-core-synch-l1-2-0.dll
fastqc_py-2025.4.24.0.dist-info/METADATA
fastqc_py-2025.4.24.0.dist-info/WHEEL
fastqc_py-2025.4.24.0.dist-info/entry_points.txt
fastqc_py-2025.4.24.0.dist-info/RECORD
