Metadata-Version: 2.4
Name: fastqc_py
Version: 2025.4.24.0
Summary: FastQC python wrapper (Windows only, with jre)
Project-URL: Repository, https://github.com/soda92/fastqc_py
Requires-Python: >=3.10
Requires-Dist: sodatools>=2025.2.16.0
